river_rrcf-0.1.1.dist-info/METADATA
river_rrcf-0.1.1.dist-info/WHEEL
river_rrcf-0.1.1.dist-info/entry_points.txt
river_rrcf-0.1.1.dist-info/licenses/LICENSE
river_rrcf/__init__.py
river_rrcf/__version__.py
river_rrcf/_vendor/rrcf.patch
river_rrcf/_vendor/rrcf/LICENSE
river_rrcf/_vendor/rrcf/__init__.py
river_rrcf/_vendor/rrcf/rrcf.py
river_rrcf/_vendor/rrcf/shingle.py
river_rrcf/rrcf.py
river_rrcf-0.1.1.dist-info/RECORD
