Metadata-Version: 2.1
Name: river-rrcf
Version: 0.1.1
Summary: Robust Random Cut Forest for the river
Keywords: rrcf,river,anomaly detection
Author-Email: Dowon <ks2515@naver.com>
License: MIT
Classifier: Programming Language :: Python :: 3
Classifier: Intended Audience :: Science/Research
Classifier: Topic :: Scientific/Engineering :: Artificial Intelligence
Project-URL: Repository, https://github.com/hellotail/river-rrcf
Requires-Python: >=3.10
Requires-Dist: river>=0.21.2
Provides-Extra: dev
Requires-Dist: polars[plot]>=1.6.0; extra == "dev"
Requires-Dist: vl-convert-python; extra == "dev"
Provides-Extra: test
Requires-Dist: pytest; extra == "test"
Requires-Dist: pytest-cov; extra == "test"
Requires-Dist: pytest-sugar; extra == "test"
Requires-Dist: tox-uv; extra == "test"
Requires-Dist: hypothesis; extra == "test"
Requires-Dist: polars; extra == "test"
Provides-Extra: lint
Requires-Dist: ruff; extra == "lint"
Requires-Dist: pre-commit>=4; extra == "lint"
Requires-Dist: pre-commit-uv; extra == "lint"
